[{"nombre":"h","puntuacion":0,"fecha":1683716295000,"duracion":10},{"nombre":"PruebaVideo","puntuacion":18,"fecha":1683724321000,"duracion":22},{"nombre":"juanito","puntuacion":125,"fecha":1683703877000,"duracion":350000000},{"nombre":"h","puntuacion":3,"fecha":1683716487000,"duracion":9},{"nombre":"Pedro","puntuacion":0,"fecha":1683703930000,"duracion":11},{"nombre":"Hola","puntuacion":0,"fecha":1683725437000,"duracion":8},{"nombre":"d","puntuacion":0,"fecha":1683725152000,"duracion":4},{"nombre":"m","puntuacion":0,"fecha":1683725101000,"duracion":5},{"nombre":"prueba12","puntuacion":0,"fecha":1683705359000,"duracion":14},{"nombre":"c","puntuacion":0,"fecha":1683724624000,"duracion":5},{"nombre":"c","puntuacion":0,"fecha":1683724886000,"duracion":6},{"nombre":"juanito","puntuacion":125,"fecha":1683703676000,"duracion":350000000},{"nombre":"g","puntuacion":0,"fecha":1683724726000,"duracion":6}]